obfusguard/__init__.py
obfusguard/core.py
ObfusGuard-0.1.0.dist-info/LICENSE
ObfusGuard-0.1.0.dist-info/METADATA
ObfusGuard-0.1.0.dist-info/WHEEL
ObfusGuard-0.1.0.dist-info/top_level.txt
ObfusGuard-0.1.0.dist-info/RECORD
