Metadata-Version: 2.1
Name: ObfusGuard
Version: 0.1.0
Summary: A multi-layered encryption and hashing algorithm.
Home-page: https://github.com/RajnishXCode/ObfusGuard
Author: Rajnish Tripathi
Author-email: rajnishtripathi2001@gmail.com
Classifier: Programming Language :: Python :: 3
Classifier: License :: OSI Approved :: MIT License
Classifier: Operating System :: OS Independent
Requires-Python: >=3.6
License-File: LICENSE
Requires-Dist: python-dotenv
